{
  "updated_at": "2026-03-23T23:44:58+09:00",
  "properties": [
    {
      "name": "カーメスト用賀馬事公苑",
      "total": 25,
      "rooms": {
        "１ＤＫ": 1,
        "１ＬＤＫ": 7,
        "２ＬＤＫ": 5,
        "３ＬＤＫ": 11,
        "２ＬＤＫＤＫ": 1
      }
    },
    {
      "name": "松が谷",
      "total": 2,
      "rooms": {
        "３ＤＫ": 2
      }
    },
    {
      "name": "横川町",
      "total": 1,
      "rooms": {
        "２ＤＫ": 1
      }
    },
    {
      "name": "松が谷第二",
      "total": 2,
      "rooms": {
        "３ＤＫ": 2
      }
    },
    {
      "name": "富士見町東",
      "total": 5,
      "rooms": {
        "２ＤＫ": 5
      }
    },
    {
      "name": "木曽",
      "total": 1,
      "rooms": {
        "２Ｋ": 1
      }
    },
    {
      "name": "町田木曽",
      "total": 43,
      "rooms": {
        "３Ｋ": 17,
        "２Ｋ": 4,
        "２ＤＫ": 22
      }
    },
    {
      "name": "大和芝中",
      "total": 1,
      "rooms": {
        "２ＤＫＳ": 1
      }
    },
    {
      "name": "清瀬台田",
      "total": 1,
      "rooms": {
        "２ＤＫ": 1
      }
    },
    {
      "name": "久留米下里",
      "total": 3,
      "rooms": {
        "２ＤＫ": 1,
        "３Ｋ": 2
      }
    },
    {
      "name": "下里第二",
      "total": 1,
      "rooms": {
        "３ＤＫ": 1
      }
    },
    {
      "name": "落合",
      "total": 9,
      "rooms": {
        "３ＤＫ": 9
      }
    },
    {
      "name": "平尾",
      "total": 7,
      "rooms": {
        "１ＤＫ": 1,
        "２ＤＫ": 2,
        "３Ｋ": 4
      }
    }
  ]
}